ranranru/__init__.py
ranranru/__version__.py
ranranru/main.py
ranranru/bcc/__init__.py
ranranru/bcc/context.py
ranranru/bcc/render.py
ranranru/elf/__init__.py
ranranru/elf/dwarf_debug_frame.py
ranranru/elf/dwarf_debug_info.py
ranranru/elf/dwarf_debug_line.py
ranranru/elf/dwarf_debug_loc.py
ranranru/elf/dwarf_location_desc.py
ranranru/elf/interpreter.py
ranranru/elf/symbol_table.py
ranranru/elf/utils.py
ranranru/program/__init__.py
ranranru/program/parse.py
ranranru/program/uprobe.py
ranranru-0.0.2.dist-info/LICENSE
ranranru-0.0.2.dist-info/METADATA
ranranru-0.0.2.dist-info/WHEEL
ranranru-0.0.2.dist-info/entry_points.txt
ranranru-0.0.2.dist-info/top_level.txt
ranranru-0.0.2.dist-info/RECORD
